sphinx_deck/__init__.py
sphinx_deck/__main__.py
sphinx_deck-0.0.1.dist-info/licenses/LICENSE
sphinx_deck-0.0.1.dist-info/METADATA
sphinx_deck-0.0.1.dist-info/WHEEL
sphinx_deck-0.0.1.dist-info/top_level.txt
sphinx_deck-0.0.1.dist-info/RECORD
