Metadata-Version: 2.4
Name: sphinx-deck
Version: 0.0.1
Summary: Sphinx extension to generate Markdown for k1LoW/deck from Sphinx documentation
Author-email: nikkie <takuyafjp+develop@gmail.com>
License: MIT License
Project-URL: Repository, https://github.com/ftnext/sphinx-deck
Keywords: Sphinx,k1LoW/deck
Classifier: Development Status :: 3 - Alpha
Classifier: License :: OSI Approved :: MIT License
Classifier: Intended Audience :: Developers
Classifier: Framework :: Sphinx
Classifier: Framework :: Sphinx :: Extension
Classifier: Topic :: Documentation
Classifier: Topic :: Documentation :: Sphinx
Classifier: Topic :: Software Development :: Documentation
Classifier: Programming Language :: Python
Classifier: Programming Language :: Python :: 3
Classifier: Programming Language :: Python :: 3 :: Only
Classifier: Programming Language :: Python :: 3.10
Classifier: Programming Language :: Python :: 3.11
Classifier: Programming Language :: Python :: 3.12
Classifier: Programming Language :: Python :: 3.13
Classifier: Programming Language :: Python :: 3.14
Requires-Python: >=3.10
License-File: LICENSE
Requires-Dist: sphinx-markdown-builder
Requires-Dist: sphinxcontrib-extdevhelper-kasane
Dynamic: license-file
